debiasing/__init__.py
debiasing/debias_prog.py
Debias_Infer-0.0.8.dist-info/LICENSE
Debias_Infer-0.0.8.dist-info/METADATA
Debias_Infer-0.0.8.dist-info/WHEEL
Debias_Infer-0.0.8.dist-info/top_level.txt
Debias_Infer-0.0.8.dist-info/RECORD
