Metadata-Version: 2.1
Name: Debias-Infer
Version: 0.0.8
Summary: Efficient Inference on High-Dimensional Linear Models With Missing Outcomes
Home-page: https://github.com/zhangyk8/Debias-Infer
Author: Yikun Zhang
Author-email: yikunzhang@foxmail.com
Classifier: Programming Language :: Python :: 3
Classifier: License :: OSI Approved :: MIT License
Classifier: Operating System :: OS Independent
Requires-Python: >=3.8
License-File: LICENSE
Requires-Dist: numpy >=1.16
Requires-Dist: scipy >=1.1.0
Requires-Dist: cvxpy[cvxopt,mosek]
Requires-Dist: scikit-learn
Requires-Dist: statsmodels
